[
    {
        "comment": "/**\n * Represents a channel within Discord.\n * @see {@link https://discord.com/developers/docs/resources/channel}\n */",
        "meta": {
            "range": [
                412,
                8582
            ],
            "filename": "Channel.js",
            "lineno": 11,
            "columnno": 0,
            "path": "/home/runner/work/gluon/gluon/src/structures",
            "code": {
                "id": "astnode100000022",
                "name": "Channel",
                "type": "ClassDeclaration",
                "paramnames": [
                    "client",
                    "data",
                    ""
                ]
            }
        },
        "classdesc": "Represents a channel within Discord.",
        "see": [
            "{@link https://discord.com/developers/docs/resources/channel}"
        ],
        "name": "Channel",
        "longname": "Channel",
        "kind": "class",
        "scope": "global",
        "undocumented": true
    },
    {
        "comment": "",
        "meta": {
            "range": [
                430,
                439
            ],
            "filename": "Channel.js",
            "lineno": 12,
            "columnno": 2,
            "path": "/home/runner/work/gluon/gluon/src/structures",
            "code": {
                "id": "astnode100000025",
                "name": "_client",
                "type": "ClassPrivateProperty"
            }
        },
        "undocumented": true,
        "name": "_client",
        "longname": "Channel#_client",
        "kind": "member",
        "memberof": "Channel",
        "scope": "instance",
        "access": "private"
    },
    {
        "comment": "",
        "meta": {
            "range": [
                442,
                447
            ],
            "filename": "Channel.js",
            "lineno": 13,
            "columnno": 2,
            "path": "/home/runner/work/gluon/gluon/src/structures",
            "code": {
                "id": "astnode100000026",
                "name": "_id",
                "type": "ClassPrivateProperty"
            }
        },
        "undocumented": true,
        "name": "_id",
        "longname": "Channel#_id",
        "kind": "member",
        "memberof": "Channel",
        "scope": "instance",
        "access": "private"
    },
    {
        "comment": "",
        "meta": {
            "range": [
                450,
                461
            ],
            "filename": "Channel.js",
            "lineno": 14,
            "columnno": 2,
            "path": "/home/runner/work/gluon/gluon/src/structures",
            "code": {
                "id": "astnode100000027",
                "name": "_guild_id",
                "type": "ClassPrivateProperty"
            }
        },
        "undocumented": true,
        "name": "_guild_id",
        "longname": "Channel#_guild_id",
        "kind": "member",
        "memberof": "Channel",
        "scope": "instance",
        "access": "private"
    },
    {
        "comment": "",
        "meta": {
            "range": [
                464,
                470
            ],
            "filename": "Channel.js",
            "lineno": 15,
            "columnno": 2,
            "path": "/home/runner/work/gluon/gluon/src/structures",
            "code": {
                "id": "astnode100000028",
                "name": "type",
                "type": "ClassPrivateProperty"
            }
        },
        "undocumented": true,
        "name": "type",
        "longname": "Channel#type",
        "kind": "member",
        "memberof": "Channel",
        "scope": "instance",
        "access": "private"
    },
    {
        "comment": "",
        "meta": {
            "range": [
                473,
                479
            ],
            "filename": "Channel.js",
            "lineno": 16,
            "columnno": 2,
            "path": "/home/runner/work/gluon/gluon/src/structures",
            "code": {
                "id": "astnode100000029",
                "name": "name",
                "type": "ClassPrivateProperty"
            }
        },
        "undocumented": true,
        "name": "name",
        "longname": "Channel#name",
        "kind": "member",
        "memberof": "Channel",
        "scope": "instance",
        "access": "private"
    },
    {
        "comment": "",
        "meta": {
            "range": [
                482,
                489
            ],
            "filename": "Channel.js",
            "lineno": 17,
            "columnno": 2,
            "path": "/home/runner/work/gluon/gluon/src/structures",
            "code": {
                "id": "astnode100000030",
                "name": "topic",
                "type": "ClassPrivateProperty"
            }
        },
        "undocumented": true,
        "name": "topic",
        "longname": "Channel#topic",
        "kind": "member",
        "memberof": "Channel",
        "scope": "instance",
        "access": "private"
    },
    {
        "comment": "",
        "meta": {
            "range": [
                492,
                513
            ],
            "filename": "Channel.js",
            "lineno": 18,
            "columnno": 2,
            "path": "/home/runner/work/gluon/gluon/src/structures",
            "code": {
                "id": "astnode100000031",
                "name": "rate_limit_per_user",
                "type": "ClassPrivateProperty"
            }
        },
        "undocumented": true,
        "name": "rate_limit_per_user",
        "longname": "Channel#rate_limit_per_user",
        "kind": "member",
        "memberof": "Channel",
        "scope": "instance",
        "access": "private"
    },
    {
        "comment": "",
        "meta": {
            "range": [
                516,
                528
            ],
            "filename": "Channel.js",
            "lineno": 19,
            "columnno": 2,
            "path": "/home/runner/work/gluon/gluon/src/structures",
            "code": {
                "id": "astnode100000032",
                "name": "_parent_id",
                "type": "ClassPrivateProperty"
            }
        },
        "undocumented": true,
        "name": "_parent_id",
        "longname": "Channel#_parent_id",
        "kind": "member",
        "memberof": "Channel",
        "scope": "instance",
        "access": "private"
    },
    {
        "comment": "",
        "meta": {
            "range": [
                531,
                544
            ],
            "filename": "Channel.js",
            "lineno": 20,
            "columnno": 2,
            "path": "/home/runner/work/gluon/gluon/src/structures",
            "code": {
                "id": "astnode100000033",
                "name": "_attributes",
                "type": "ClassPrivateProperty"
            }
        },
        "undocumented": true,
        "name": "_attributes",
        "longname": "Channel#_attributes",
        "kind": "member",
        "memberof": "Channel",
        "scope": "instance",
        "access": "private"
    },
    {
        "comment": "",
        "meta": {
            "range": [
                547,
                562
            ],
            "filename": "Channel.js",
            "lineno": 21,
            "columnno": 2,
            "path": "/home/runner/work/gluon/gluon/src/structures",
            "code": {
                "id": "astnode100000034",
                "name": "_cacheOptions",
                "type": "ClassPrivateProperty"
            }
        },
        "undocumented": true,
        "name": "_cacheOptions",
        "longname": "Channel#_cacheOptions",
        "kind": "member",
        "memberof": "Channel",
        "scope": "instance",
        "access": "private"
    },
    {
        "comment": "",
        "meta": {
            "range": [
                565,
                575
            ],
            "filename": "Channel.js",
            "lineno": 22,
            "columnno": 2,
            "path": "/home/runner/work/gluon/gluon/src/structures",
            "code": {
                "id": "astnode100000035",
                "name": "messages",
                "type": "ClassPrivateProperty"
            }
        },
        "undocumented": true,
        "name": "messages",
        "longname": "Channel#messages",
        "kind": "member",
        "memberof": "Channel",
        "scope": "instance",
        "access": "private"
    },
    {
        "comment": "/**\n   * Creates the base structure for a channel.\n   * @param {Client} client The client instance.\n   * @param {Object} data Raw channel data.\n   * @param {String} guild_id The ID of the guild that this channel belongs to.\n   * @see {@link https://discord.com/developers/docs/resources/channel#channel-object-channel-structure}\n   */",
        "meta": {
            "range": [
                915,
                3772
            ],
            "filename": "Channel.js",
            "lineno": 30,
            "columnno": 2,
            "path": "/home/runner/work/gluon/gluon/src/structures",
            "code": {
                "id": "astnode100000036",
                "name": "Channel",
                "type": "MethodDefinition",
                "paramnames": [
                    "client",
                    "data",
                    ""
                ]
            },
            "vars": {
                "": null
            }
        },
        "description": "Creates the base structure for a channel.",
        "params": [
            {
                "type": {
                    "names": [
                        "Client"
                    ]
                },
                "description": "The client instance.",
                "name": "client"
            },
            {
                "type": {
                    "names": [
                        "Object"
                    ]
                },
                "description": "Raw channel data.",
                "name": "data"
            },
            {
                "type": {
                    "names": [
                        "String"
                    ]
                },
                "description": "The ID of the guild that this channel belongs to.",
                "name": "guild_id"
            }
        ],
        "see": [
            "{@link https://discord.com/developers/docs/resources/channel#channel-object-channel-structure}"
        ],
        "name": "Channel",
        "longname": "Channel",
        "kind": "class",
        "scope": "global",
        "undocumented": true
    },
    {
        "comment": "/**\n * Represents a channel within Discord.\n * @see {@link https://discord.com/developers/docs/resources/channel}\n */",
        "meta": {
            "range": [
                412,
                8582
            ],
            "filename": "Channel.js",
            "lineno": 11,
            "columnno": 0,
            "path": "/home/runner/work/gluon/gluon/src/structures",
            "code": {
                "id": "astnode100000022",
                "name": "Channel",
                "type": "ClassDeclaration",
                "paramnames": [
                    "client",
                    "data",
                    ""
                ]
            }
        },
        "name": "Channel",
        "longname": "Channel",
        "kind": "class",
        "classdesc": "Represents a channel within Discord.",
        "see": [
            "{@link https://discord.com/developers/docs/resources/channel}"
        ],
        "scope": "global",
        "description": "Creates the base structure for a channel.",
        "params": [
            {
                "type": {
                    "names": [
                        "Client"
                    ]
                },
                "description": "The client instance.",
                "name": "client"
            },
            {
                "type": {
                    "names": [
                        "Object"
                    ]
                },
                "description": "Raw channel data.",
                "name": "data"
            },
            {
                "type": {
                    "names": [
                        "String"
                    ]
                },
                "description": "The ID of the guild that this channel belongs to.",
                "name": "guild_id"
            }
        ]
    },
    {
        "comment": "",
        "meta": {
            "range": [
                943,
                951
            ],
            "filename": "Channel.js",
            "lineno": 30,
            "columnno": 30,
            "path": "/home/runner/work/gluon/gluon/src/structures",
            "code": {
                "id": "astnode100000043",
                "name": "guild_id",
                "type": "Identifier",
                "value": "guild_id"
            }
        },
        "undocumented": true,
        "name": "guild_id",
        "longname": "guild_id",
        "kind": "member",
        "scope": "global"
    },
    {
        "comment": "/**\n     * The client instance.\n     * @type {Client}\n     * @private\n     */",
        "meta": {
            "range": [
                1048,
                1070
            ],
            "filename": "Channel.js",
            "lineno": 36,
            "columnno": 4,
            "path": "/home/runner/work/gluon/gluon/src/structures",
            "code": {
                "id": "astnode100000048",
                "name": "this.",
                "type": "Identifier",
                "value": "client",
                "paramnames": []
            }
        },
        "description": "The client instance.",
        "type": {
            "names": [
                "Client"
            ]
        },
        "access": "private",
        "name": "Channel",
        "longname": "Channel.Channel",
        "kind": "member",
        "memberof": "Channel",
        "scope": "static"
    },
    {
        "comment": "/**\n     * The id of the channel.\n     * @type {BigInt}\n     * @private\n     */",
        "meta": {
            "range": [
                1161,
                1188
            ],
            "filename": "Channel.js",
            "lineno": 43,
            "columnno": 4,
            "path": "/home/runner/work/gluon/gluon/src/structures",
            "code": {
                "id": "astnode100000055",
                "name": "this.",
                "type": "CallExpression",
                "value": "",
                "paramnames": []
            }
        },
        "description": "The id of the channel.",
        "type": {
            "names": [
                "BigInt"
            ]
        },
        "access": "private",
        "name": "Channel",
        "longname": "Channel.Channel",
        "kind": "member",
        "memberof": "Channel",
        "scope": "static"
    },
    {
        "comment": "/**\n     * The ID of the guild that this channel belongs to.\n     * @type {BigInt}\n     * @private\n     */",
        "meta": {
            "range": [
                1306,
                1340
            ],
            "filename": "Channel.js",
            "lineno": 50,
            "columnno": 4,
            "path": "/home/runner/work/gluon/gluon/src/structures",
            "code": {
                "id": "astnode100000066",
                "name": "this.",
                "type": "CallExpression",
                "value": "",
                "paramnames": []
            }
        },
        "description": "The ID of the guild that this channel belongs to.",
        "type": {
            "names": [
                "BigInt"
            ]
        },
        "access": "private",
        "name": "Channel",
        "longname": "Channel.Channel",
        "kind": "member",
        "memberof": "Channel",
        "scope": "static"
    },
    {
        "comment": "/**\n     * The type of channel.\n     * @type {Number}\n     * @private\n     */",
        "meta": {
            "range": [
                1429,
                1451
            ],
            "filename": "Channel.js",
            "lineno": 57,
            "columnno": 4,
            "path": "/home/runner/work/gluon/gluon/src/structures",
            "code": {
                "id": "astnode100000075",
                "name": "this.",
                "type": "MemberExpression",
                "value": "data.type",
                "paramnames": []
            }
        },
        "description": "The type of channel.",
        "type": {
            "names": [
                "Number"
            ]
        },
        "access": "private",
        "name": "Channel",
        "longname": "Channel.Channel",
        "kind": "member",
        "memberof": "Channel",
        "scope": "static"
    },
    {
        "comment": "",
        "meta": {
            "range": [
                1464,
                1516
            ],
            "filename": "Channel.js",
            "lineno": 59,
            "columnno": 10,
            "path": "/home/runner/work/gluon/gluon/src/structures",
            "code": {
                "id": "astnode100000084",
                "name": "existing",
                "type": "LogicalExpression",
                "value": ""
            }
        },
        "undocumented": true,
        "name": "existing",
        "longname": "<anonymous>~existing",
        "kind": "constant",
        "memberof": "<anonymous>",
        "scope": "inner",
        "params": []
    },
    {
        "comment": "",
        "meta": {
            "range": [
                1643,
                1665
            ],
            "filename": "Channel.js",
            "lineno": 66,
            "columnno": 38,
            "path": "/home/runner/work/gluon/gluon/src/structures",
            "code": {
                "id": "astnode100000097",
                "name": "this.",
                "type": "MemberExpression",
                "value": "data.name",
                "paramnames": []
            }
        },
        "undocumented": true,
        "name": "Channel",
        "longname": "Channel.Channel",
        "kind": "member",
        "memberof": "Channel",
        "scope": "static"
    },
    {
        "comment": "",
        "meta": {
            "range": [
                1788,
                1814
            ],
            "filename": "Channel.js",
            "lineno": 72,
            "columnno": 6,
            "path": "/home/runner/work/gluon/gluon/src/structures",
            "code": {
                "id": "astnode100000122",
                "name": "this.",
                "type": "MemberExpression",
                "value": "existing.name",
                "paramnames": []
            }
        },
        "undocumented": true,
        "name": "Channel",
        "longname": "Channel.Channel",
        "kind": "member",
        "memberof": "Channel",
        "scope": "static"
    },
    {
        "comment": "",
        "meta": {
            "range": [
                1944,
                1968
            ],
            "filename": "Channel.js",
            "lineno": 79,
            "columnno": 39,
            "path": "/home/runner/work/gluon/gluon/src/structures",
            "code": {
                "id": "astnode100000138",
                "name": "this.",
                "type": "MemberExpression",
                "value": "data.topic",
                "paramnames": []
            }
        },
        "undocumented": true,
        "name": "Channel",
        "longname": "Channel.Channel",
        "kind": "member",
        "memberof": "Channel",
        "scope": "static"
    },
    {
        "comment": "",
        "meta": {
            "range": [
                2093,
                2121
            ],
            "filename": "Channel.js",
            "lineno": 85,
            "columnno": 6,
            "path": "/home/runner/work/gluon/gluon/src/structures",
            "code": {
                "id": "astnode100000163",
                "name": "this.",
                "type": "MemberExpression",
                "value": "existing.topic",
                "paramnames": []
            }
        },
        "undocumented": true,
        "name": "Channel",
        "longname": "Channel.Channel",
        "kind": "member",
        "memberof": "Channel",
        "scope": "static"
    },
    {
        "comment": "",
        "meta": {
            "range": [
                2288,
                2340
            ],
            "filename": "Channel.js",
            "lineno": 93,
            "columnno": 6,
            "path": "/home/runner/work/gluon/gluon/src/structures",
            "code": {
                "id": "astnode100000179",
                "name": "this.",
                "type": "MemberExpression",
                "value": "data.rate_limit_per_user",
                "paramnames": []
            }
        },
        "undocumented": true,
        "name": "Channel",
        "longname": "Channel.Channel",
        "kind": "member",
        "memberof": "Channel",
        "scope": "static"
    },
    {
        "comment": "",
        "meta": {
            "range": [
                2490,
                2543
            ],
            "filename": "Channel.js",
            "lineno": 99,
            "columnno": 6,
            "path": "/home/runner/work/gluon/gluon/src/structures",
            "code": {
                "id": "astnode100000204",
                "name": "this.",
                "type": "MemberExpression",
                "value": "existing.rateLimitPerUser",
                "paramnames": []
            }
        },
        "undocumented": true,
        "name": "Channel",
        "longname": "Channel.Channel",
        "kind": "member",
        "memberof": "Channel",
        "scope": "static"
    },
    {
        "comment": "/**\n       * The id of the parent channel.\n       * @type {BigInt?}\n       * @private\n       */",
        "meta": {
            "range": [
                2699,
                2740
            ],
            "filename": "Channel.js",
            "lineno": 107,
            "columnno": 6,
            "path": "/home/runner/work/gluon/gluon/src/structures",
            "code": {
                "id": "astnode100000221",
                "name": "this.",
                "type": "CallExpression",
                "value": "",
                "paramnames": []
            }
        },
        "description": "The id of the parent channel.",
        "type": {
            "names": [
                "BigInt"
            ]
        },
        "nullable": true,
        "access": "private",
        "name": "Channel",
        "longname": "Channel.Channel",
        "kind": "member",
        "memberof": "Channel",
        "scope": "static"
    },
    {
        "comment": "",
        "meta": {
            "range": [
                2912,
                2948
            ],
            "filename": "Channel.js",
            "lineno": 114,
            "columnno": 6,
            "path": "/home/runner/work/gluon/gluon/src/structures",
            "code": {
                "id": "astnode100000254",
                "name": "this.",
                "type": "MemberExpression",
                "value": "existing.parentId",
                "paramnames": []
            }
        },
        "undocumented": true,
        "name": "Channel",
        "longname": "Channel.Channel",
        "kind": "member",
        "memberof": "Channel",
        "scope": "static"
    },
    {
        "comment": "/**\n     * The attributes of the channel.\n     * @type {Number}\n     * @private\n     */",
        "meta": {
            "range": [
                3047,
                3088
            ],
            "filename": "Channel.js",
            "lineno": 121,
            "columnno": 4,
            "path": "/home/runner/work/gluon/gluon/src/structures",
            "code": {
                "id": "astnode100000263",
                "name": "this.",
                "type": "LogicalExpression",
                "value": "",
                "paramnames": []
            }
        },
        "description": "The attributes of the channel.",
        "type": {
            "names": [
                "Number"
            ]
        },
        "access": "private",
        "name": "Channel",
        "longname": "Channel.Channel",
        "kind": "member",
        "memberof": "Channel",
        "scope": "static"
    },
    {
        "comment": "",
        "meta": {
            "range": [
                3151,
                3180
            ],
            "filename": "Channel.js",
            "lineno": 124,
            "columnno": 6,
            "path": "/home/runner/work/gluon/gluon/src/structures",
            "code": {
                "id": "astnode100000286",
                "name": "this.",
                "type": "BinaryExpression",
                "value": "",
                "paramnames": []
            }
        },
        "undocumented": true,
        "name": "Channel",
        "longname": "Channel.Channel",
        "kind": "member",
        "memberof": "Channel",
        "scope": "static"
    },
    {
        "comment": "",
        "meta": {
            "range": [
                3263,
                3292
            ],
            "filename": "Channel.js",
            "lineno": 126,
            "columnno": 6,
            "path": "/home/runner/work/gluon/gluon/src/structures",
            "code": {
                "id": "astnode100000309",
                "name": "this.",
                "type": "BinaryExpression",
                "value": "",
                "paramnames": []
            }
        },
        "undocumented": true,
        "name": "Channel",
        "longname": "Channel.Channel",
        "kind": "member",
        "memberof": "Channel",
        "scope": "static"
    },
    {
        "comment": "/**\n     * The cache options for this channel.\n     * @type {ChannelCacheOptions}\n     * @private\n     */",
        "meta": {
            "range": [
                3409,
                3537
            ],
            "filename": "Channel.js",
            "lineno": 133,
            "columnno": 4,
            "path": "/home/runner/work/gluon/gluon/src/structures",
            "code": {
                "id": "astnode100000318",
                "name": "this.",
                "type": "ConditionalExpression",
                "value": "",
                "paramnames": []
            }
        },
        "description": "The cache options for this channel.",
        "type": {
            "names": [
                "ChannelCacheOptions"
            ]
        },
        "access": "private",
        "name": "Channel",
        "longname": "Channel.Channel",
        "kind": "member",
        "memberof": "Channel",
        "scope": "static"
    },
    {
        "comment": "/**\n     * The message manager for this channel.\n     * @type {ChannelMessageManager}\n     * @private\n     */",
        "meta": {
            "range": [
                3658,
                3767
            ],
            "filename": "Channel.js",
            "lineno": 142,
            "columnno": 4,
            "path": "/home/runner/work/gluon/gluon/src/structures",
            "code": {
                "id": "astnode100000334",
                "name": "this.",
                "type": "ConditionalExpression",
                "value": "",
                "paramnames": []
            }
        },
        "description": "The message manager for this channel.",
        "type": {
            "names": [
                "ChannelMessageManager"
            ]
        },
        "access": "private",
        "name": "Channel",
        "longname": "Channel.Channel",
        "kind": "member",
        "memberof": "Channel",
        "scope": "static"
    },
    {
        "comment": "/**\n   * Sends a message to this channel.\n   * @param {String} content The message content.\n   * @param {Object} param1 Embeds, components and files to include with the message.\n   * @returns {Promise<Message>}\n   * @see {@link https://discord.com/developers/docs/resources/channel#create-message}\n   * @method\n   * @public\n   * @async\n   * @throws {Error | TypeError}\n   */",
        "meta": {
            "range": [
                4153,
                5971
            ],
            "filename": "Channel.js",
            "lineno": 158,
            "columnno": 2,
            "path": "/home/runner/work/gluon/gluon/src/structures",
            "code": {
                "id": "astnode100000348",
                "name": "Channel#send",
                "type": "MethodDefinition",
                "paramnames": [
                    "content",
                    ""
                ]
            },
            "vars": {
                "": null
            }
        },
        "description": "Sends a message to this channel.",
        "params": [
            {
                "type": {
                    "names": [
                        "String"
                    ]
                },
                "description": "The message content.",
                "name": "content"
            },
            {
                "type": {
                    "names": [
                        "Object"
                    ]
                },
                "description": "Embeds, components and files to include with the message.",
                "name": "param1"
            }
        ],
        "returns": [
            {
                "type": {
                    "names": [
                        "Promise.<Message>"
                    ]
                }
            }
        ],
        "see": [
            "{@link https://discord.com/developers/docs/resources/channel#create-message}"
        ],
        "kind": "function",
        "access": "public",
        "async": true,
        "exceptions": [
            {
                "type": {
                    "names": [
                        "Error",
                        "TypeError"
                    ]
                }
            }
        ],
        "name": "send",
        "longname": "Channel#send",
        "memberof": "Channel",
        "scope": "instance"
    },
    {
        "comment": "",
        "meta": {
            "range": [
                4184,
                4194
            ],
            "filename": "Channel.js",
            "lineno": 160,
            "columnno": 6,
            "path": "/home/runner/work/gluon/gluon/src/structures",
            "code": {
                "id": "astnode100000354",
                "name": "components",
                "type": "Identifier",
                "value": "components"
            }
        },
        "undocumented": true,
        "name": "components",
        "longname": "components",
        "kind": "member",
        "scope": "global"
    },
    {
        "comment": "",
        "meta": {
            "range": [
                4196,
                4201
            ],
            "filename": "Channel.js",
            "lineno": 160,
            "columnno": 18,
            "path": "/home/runner/work/gluon/gluon/src/structures",
            "code": {
                "id": "astnode100000356",
                "name": "files",
                "type": "Identifier",
                "value": "files"
            }
        },
        "undocumented": true,
        "name": "files",
        "longname": "files",
        "kind": "member",
        "scope": "global"
    },
    {
        "comment": "",
        "meta": {
            "range": [
                4203,
                4209
            ],
            "filename": "Channel.js",
            "lineno": 160,
            "columnno": 25,
            "path": "/home/runner/work/gluon/gluon/src/structures",
            "code": {
                "id": "astnode100000358",
                "name": "embeds",
                "type": "Identifier",
                "value": "embeds"
            }
        },
        "undocumented": true,
        "name": "embeds",
        "longname": "embeds",
        "kind": "member",
        "scope": "global"
    },
    {
        "comment": "",
        "meta": {
            "range": [
                4211,
                4235
            ],
            "filename": "Channel.js",
            "lineno": 160,
            "columnno": 33,
            "path": "/home/runner/work/gluon/gluon/src/structures",
            "code": {
                "id": "astnode100000360",
                "name": "suppressMentions",
                "type": "AssignmentPattern",
                "value": "suppressMentions"
            }
        },
        "undocumented": true,
        "name": "suppressMentions",
        "longname": "suppressMentions",
        "kind": "member",
        "scope": "global"
    },
    {
        "comment": "",
        "meta": {
            "range": [
                5419,
                5428
            ],
            "filename": "Channel.js",
            "lineno": 202,
            "columnno": 10,
            "path": "/home/runner/work/gluon/gluon/src/structures",
            "code": {
                "id": "astnode100000502",
                "name": "body",
                "type": "ObjectExpression",
                "value": "{}"
            }
        },
        "undocumented": true,
        "name": "body",
        "longname": "<anonymous>~body",
        "kind": "constant",
        "memberof": "<anonymous>",
        "scope": "inner",
        "params": []
    },
    {
        "comment": "",
        "meta": {
            "range": [
                5448,
                5470
            ],
            "filename": "Channel.js",
            "lineno": 204,
            "columnno": 17,
            "path": "/home/runner/work/gluon/gluon/src/structures",
            "code": {
                "id": "astnode100000508",
                "name": "body.content",
                "type": "Identifier",
                "funcscope": "<anonymous>",
                "value": "content",
                "paramnames": []
            }
        },
        "undocumented": true,
        "name": "content",
        "longname": "<anonymous>~body.content",
        "kind": "member",
        "memberof": "<anonymous>~body",
        "scope": "static"
    },
    {
        "comment": "",
        "meta": {
            "range": [
                5489,
                5509
            ],
            "filename": "Channel.js",
            "lineno": 206,
            "columnno": 16,
            "path": "/home/runner/work/gluon/gluon/src/structures",
            "code": {
                "id": "astnode100000516",
                "name": "body.embeds",
                "type": "Identifier",
                "funcscope": "<anonymous>",
                "value": "embeds",
                "paramnames": []
            }
        },
        "undocumented": true,
        "name": "embeds",
        "longname": "<anonymous>~body.embeds",
        "kind": "member",
        "memberof": "<anonymous>~body",
        "scope": "static"
    },
    {
        "comment": "",
        "meta": {
            "range": [
                5531,
                5559
            ],
            "filename": "Channel.js",
            "lineno": 207,
            "columnno": 20,
            "path": "/home/runner/work/gluon/gluon/src/structures",
            "code": {
                "id": "astnode100000524",
                "name": "body.components",
                "type": "Identifier",
                "funcscope": "<anonymous>",
                "value": "components",
                "paramnames": []
            }
        },
        "undocumented": true,
        "name": "components",
        "longname": "<anonymous>~body.components",
        "kind": "member",
        "memberof": "<anonymous>~body",
        "scope": "static"
    },
    {
        "comment": "",
        "meta": {
            "range": [
                5576,
                5594
            ],
            "filename": "Channel.js",
            "lineno": 208,
            "columnno": 15,
            "path": "/home/runner/work/gluon/gluon/src/structures",
            "code": {
                "id": "astnode100000532",
                "name": "body.files",
                "type": "Identifier",
                "funcscope": "<anonymous>",
                "value": "files",
                "paramnames": []
            }
        },
        "undocumented": true,
        "name": "files",
        "longname": "<anonymous>~body.files",
        "kind": "member",
        "memberof": "<anonymous>~body",
        "scope": "static"
    },
    {
        "comment": "",
        "meta": {
            "range": [
                5638,
                5664
            ],
            "filename": "Channel.js",
            "lineno": 210,
            "columnno": 6,
            "path": "/home/runner/work/gluon/gluon/src/structures",
            "code": {
                "id": "astnode100000543",
                "name": "body.allowed_mentions",
                "type": "ObjectExpression",
                "funcscope": "<anonymous>",
                "value": "{}",
                "paramnames": []
            }
        },
        "undocumented": true,
        "name": "allowed_mentions",
        "longname": "<anonymous>~body.allowed_mentions",
        "kind": "member",
        "memberof": "<anonymous>~body",
        "scope": "static"
    },
    {
        "comment": "",
        "meta": {
            "range": [
                5672,
                5704
            ],
            "filename": "Channel.js",
            "lineno": 211,
            "columnno": 6,
            "path": "/home/runner/work/gluon/gluon/src/structures",
            "code": {
                "id": "astnode100000549",
                "name": "body.allowed_mentions.parse",
                "type": "ArrayExpression",
                "funcscope": "<anonymous>",
                "value": "[]",
                "paramnames": []
            }
        },
        "undocumented": true,
        "name": "allowed_mentions.parse",
        "longname": "<anonymous>~body.allowed_mentions.parse",
        "kind": "member",
        "memberof": "<anonymous>~body",
        "scope": "static"
    },
    {
        "comment": "",
        "meta": {
            "range": [
                5723,
                5832
            ],
            "filename": "Channel.js",
            "lineno": 214,
            "columnno": 10,
            "path": "/home/runner/work/gluon/gluon/src/structures",
            "code": {
                "id": "astnode100000557",
                "name": "data",
                "type": "AwaitExpression",
                "value": ""
            }
        },
        "undocumented": true,
        "name": "data",
        "longname": "<anonymous>~data",
        "kind": "constant",
        "memberof": "<anonymous>",
        "scope": "inner",
        "params": []
    },
    {
        "comment": "",
        "meta": {
            "range": [
                5887,
                5906
            ],
            "filename": "Channel.js",
            "lineno": 221,
            "columnno": 6,
            "path": "/home/runner/work/gluon/gluon/src/structures",
            "code": {
                "id": "astnode100000584",
                "name": "channel_id",
                "type": "MemberExpression",
                "value": "this.id"
            }
        },
        "undocumented": true,
        "name": "channel_id",
        "longname": "channel_id",
        "kind": "member",
        "scope": "global"
    },
    {
        "comment": "",
        "meta": {
            "range": [
                5914,
                5936
            ],
            "filename": "Channel.js",
            "lineno": 222,
            "columnno": 6,
            "path": "/home/runner/work/gluon/gluon/src/structures",
            "code": {
                "id": "astnode100000588",
                "name": "guild_id",
                "type": "MemberExpression",
                "value": "this.guildId"
            }
        },
        "undocumented": true,
        "name": "guild_id",
        "longname": "guild_id",
        "kind": "member",
        "scope": "global"
    },
    {
        "comment": "",
        "meta": {
            "range": [
                5944,
                5958
            ],
            "filename": "Channel.js",
            "lineno": 223,
            "columnno": 6,
            "path": "/home/runner/work/gluon/gluon/src/structures",
            "code": {
                "id": "astnode100000592",
                "name": "nocache",
                "type": "Literal",
                "value": false
            }
        },
        "undocumented": true,
        "name": "nocache",
        "longname": "nocache",
        "kind": "member",
        "scope": "global"
    },
    {
        "comment": "/**\n   * Returns the mention for this channel.\n   * @type {String}\n   * @readonly\n   * @public\n   */",
        "meta": {
            "range": [
                6078,
                6125
            ],
            "filename": "Channel.js",
            "lineno": 233,
            "columnno": 2,
            "path": "/home/runner/work/gluon/gluon/src/structures",
            "code": {
                "id": "astnode100000594",
                "name": "Channel#mention",
                "type": "MethodDefinition",
                "paramnames": []
            },
            "vars": {
                "": null
            }
        },
        "description": "Returns the mention for this channel.",
        "type": {
            "names": [
                "String"
            ]
        },
        "readonly": true,
        "access": "public",
        "name": "mention",
        "longname": "Channel#mention",
        "kind": "member",
        "memberof": "Channel",
        "scope": "instance",
        "params": []
    },
    {
        "comment": "/**\n   * Whether this channel is marked as NSFW or not.\n   * @readonly\n   * @returns {Boolean}\n   * @public\n   */",
        "meta": {
            "range": [
                6245,
                6318
            ],
            "filename": "Channel.js",
            "lineno": 243,
            "columnno": 2,
            "path": "/home/runner/work/gluon/gluon/src/structures",
            "code": {
                "id": "astnode100000605",
                "name": "Channel#nsfw",
                "type": "MethodDefinition",
                "paramnames": []
            },
            "vars": {
                "": null
            }
        },
        "description": "Whether this channel is marked as NSFW or not.",
        "readonly": true,
        "returns": [
            {
                "type": {
                    "names": [
                        "Boolean"
                    ]
                }
            }
        ],
        "access": "public",
        "name": "nsfw",
        "longname": "Channel#nsfw",
        "kind": "member",
        "memberof": "Channel",
        "scope": "instance",
        "params": []
    },
    {
        "comment": "/**\n   * The guild that this channel belongs to.\n   * @type {Guild?}\n   * @readonly\n   * @public\n   */",
        "meta": {
            "range": [
                6427,
                6503
            ],
            "filename": "Channel.js",
            "lineno": 253,
            "columnno": 2,
            "path": "/home/runner/work/gluon/gluon/src/structures",
            "code": {
                "id": "astnode100000622",
                "name": "Channel#guild",
                "type": "MethodDefinition",
                "paramnames": []
            },
            "vars": {
                "": null
            }
        },
        "description": "The guild that this channel belongs to.",
        "type": {
            "names": [
                "Guild"
            ]
        },
        "nullable": true,
        "readonly": true,
        "access": "public",
        "name": "guild",
        "longname": "Channel#guild",
        "kind": "member",
        "memberof": "Channel",
        "scope": "instance",
        "params": []
    },
    {
        "comment": "/**\n   * The parent channel.\n   * @type {Channel?}\n   * @readonly\n   * @public\n   */",
        "meta": {
            "range": [
                6594,
                6707
            ],
            "filename": "Channel.js",
            "lineno": 263,
            "columnno": 2,
            "path": "/home/runner/work/gluon/gluon/src/structures",
            "code": {
                "id": "astnode100000641",
                "name": "Channel#parent",
                "type": "MethodDefinition",
                "paramnames": []
            },
            "vars": {
                "": null
            }
        },
        "description": "The parent channel.",
        "type": {
            "names": [
                "Channel"
            ]
        },
        "nullable": true,
        "readonly": true,
        "access": "public",
        "name": "parent",
        "longname": "Channel#parent",
        "kind": "member",
        "memberof": "Channel",
        "scope": "instance",
        "params": []
    },
    {
        "comment": "/**\n   * The ID of the channel.\n   * @type {String}\n   * @readonly\n   * @public\n   */",
        "meta": {
            "range": [
                6799,
                6843
            ],
            "filename": "Channel.js",
            "lineno": 275,
            "columnno": 2,
            "path": "/home/runner/work/gluon/gluon/src/structures",
            "code": {
                "id": "astnode100000654",
                "name": "Channel#id",
                "type": "MethodDefinition",
                "paramnames": []
            },
            "vars": {
                "": null
            }
        },
        "description": "The ID of the channel.",
        "type": {
            "names": [
                "String"
            ]
        },
        "readonly": true,
        "access": "public",
        "name": "id",
        "longname": "Channel#id",
        "kind": "member",
        "memberof": "Channel",
        "scope": "instance",
        "params": []
    },
    {
        "comment": "/**\n   * The ID of the guild that this channel belongs to.\n   * @type {String}\n   * @readonly\n   * @public\n   */",
        "meta": {
            "range": [
                6962,
                7017
            ],
            "filename": "Channel.js",
            "lineno": 285,
            "columnno": 2,
            "path": "/home/runner/work/gluon/gluon/src/structures",
            "code": {
                "id": "astnode100000665",
                "name": "Channel#guildId",
                "type": "MethodDefinition",
                "paramnames": []
            },
            "vars": {
                "": null
            }
        },
        "description": "The ID of the guild that this channel belongs to.",
        "type": {
            "names": [
                "String"
            ]
        },
        "readonly": true,
        "access": "public",
        "name": "guildId",
        "longname": "Channel#guildId",
        "kind": "member",
        "memberof": "Channel",
        "scope": "instance",
        "params": []
    },
    {
        "comment": "/**\n   * The ID of the parent channel.\n   * @type {String?}\n   * @readonly\n   * @public\n   */",
        "meta": {
            "range": [
                7117,
                7200
            ],
            "filename": "Channel.js",
            "lineno": 295,
            "columnno": 2,
            "path": "/home/runner/work/gluon/gluon/src/structures",
            "code": {
                "id": "astnode100000676",
                "name": "Channel#parentId",
                "type": "MethodDefinition",
                "paramnames": []
            },
            "vars": {
                "": null
            }
        },
        "description": "The ID of the parent channel.",
        "type": {
            "names": [
                "String"
            ]
        },
        "nullable": true,
        "readonly": true,
        "access": "public",
        "name": "parentId",
        "longname": "Channel#parentId",
        "kind": "member",
        "memberof": "Channel",
        "scope": "instance",
        "params": []
    },
    {
        "comment": "/**\n   * The type of channel.\n   * @type {Number}\n   * @readonly\n   * @public\n   */",
        "meta": {
            "range": [
                7290,
                7329
            ],
            "filename": "Channel.js",
            "lineno": 305,
            "columnno": 2,
            "path": "/home/runner/work/gluon/gluon/src/structures",
            "code": {
                "id": "astnode100000693",
                "name": "Channel#type",
                "type": "MethodDefinition",
                "paramnames": []
            },
            "vars": {
                "": null
            }
        },
        "description": "The type of channel.",
        "type": {
            "names": [
                "Number"
            ]
        },
        "readonly": true,
        "access": "public",
        "name": "type",
        "longname": "Channel#type",
        "kind": "member",
        "memberof": "Channel",
        "scope": "instance",
        "params": []
    },
    {
        "comment": "/**\n   * The name of the channel.\n   * @type {String?}\n   * @readonly\n   * @public\n   */",
        "meta": {
            "range": [
                7424,
                7463
            ],
            "filename": "Channel.js",
            "lineno": 315,
            "columnno": 2,
            "path": "/home/runner/work/gluon/gluon/src/structures",
            "code": {
                "id": "astnode100000702",
                "name": "Channel#name",
                "type": "MethodDefinition",
                "paramnames": []
            },
            "vars": {
                "": null
            }
        },
        "description": "The name of the channel.",
        "type": {
            "names": [
                "String"
            ]
        },
        "nullable": true,
        "readonly": true,
        "access": "public",
        "name": "name",
        "longname": "Channel#name",
        "kind": "member",
        "memberof": "Channel",
        "scope": "instance",
        "params": []
    },
    {
        "comment": "/**\n   * The topic of the channel.\n   * @type {String?}\n   * @readonly\n   * @public\n   */",
        "meta": {
            "range": [
                7559,
                7600
            ],
            "filename": "Channel.js",
            "lineno": 325,
            "columnno": 2,
            "path": "/home/runner/work/gluon/gluon/src/structures",
            "code": {
                "id": "astnode100000711",
                "name": "Channel#topic",
                "type": "MethodDefinition",
                "paramnames": []
            },
            "vars": {
                "": null
            }
        },
        "description": "The topic of the channel.",
        "type": {
            "names": [
                "String"
            ]
        },
        "nullable": true,
        "readonly": true,
        "access": "public",
        "name": "topic",
        "longname": "Channel#topic",
        "kind": "member",
        "memberof": "Channel",
        "scope": "instance",
        "params": []
    },
    {
        "comment": "/**\n   * The message send cooldown for the channel.\n   * @type {Number?}\n   * @readonly\n   * @public\n   */",
        "meta": {
            "range": [
                7713,
                7779
            ],
            "filename": "Channel.js",
            "lineno": 335,
            "columnno": 2,
            "path": "/home/runner/work/gluon/gluon/src/structures",
            "code": {
                "id": "astnode100000720",
                "name": "Channel#rateLimitPerUser",
                "type": "MethodDefinition",
                "paramnames": []
            },
            "vars": {
                "": null
            }
        },
        "description": "The message send cooldown for the channel.",
        "type": {
            "names": [
                "Number"
            ]
        },
        "nullable": true,
        "readonly": true,
        "access": "public",
        "name": "rateLimitPerUser",
        "longname": "Channel#rateLimitPerUser",
        "kind": "member",
        "memberof": "Channel",
        "scope": "instance",
        "params": []
    },
    {
        "comment": "/**\n   * The cache options for this channel.\n   * @type {ChannelCacheOptions}\n   * @readonly\n   * @public\n   */",
        "meta": {
            "range": [
                7897,
                7954
            ],
            "filename": "Channel.js",
            "lineno": 345,
            "columnno": 2,
            "path": "/home/runner/work/gluon/gluon/src/structures",
            "code": {
                "id": "astnode100000729",
                "name": "Channel#_cacheOptions",
                "type": "MethodDefinition",
                "paramnames": []
            },
            "vars": {
                "": null
            }
        },
        "description": "The cache options for this channel.",
        "type": {
            "names": [
                "ChannelCacheOptions"
            ]
        },
        "readonly": true,
        "access": "public",
        "name": "_cacheOptions",
        "longname": "Channel#_cacheOptions",
        "kind": "member",
        "memberof": "Channel",
        "scope": "instance",
        "params": []
    },
    {
        "comment": "/**\n   * The messages in this channel.\n   * @type {ChannelMessageManager}\n   * @readonly\n   * @public\n   */",
        "meta": {
            "range": [
                8068,
                8115
            ],
            "filename": "Channel.js",
            "lineno": 355,
            "columnno": 2,
            "path": "/home/runner/work/gluon/gluon/src/structures",
            "code": {
                "id": "astnode100000738",
                "name": "Channel#messages",
                "type": "MethodDefinition",
                "paramnames": []
            },
            "vars": {
                "": null
            }
        },
        "description": "The messages in this channel.",
        "type": {
            "names": [
                "ChannelMessageManager"
            ]
        },
        "readonly": true,
        "access": "public",
        "name": "messages",
        "longname": "Channel#messages",
        "kind": "member",
        "memberof": "Channel",
        "scope": "instance",
        "params": []
    },
    {
        "comment": "/**\n   * @method\n   * @public\n   */",
        "meta": {
            "range": [
                8157,
                8209
            ],
            "filename": "Channel.js",
            "lineno": 363,
            "columnno": 2,
            "path": "/home/runner/work/gluon/gluon/src/structures",
            "code": {
                "id": "astnode100000747",
                "name": "Channel#toString",
                "type": "MethodDefinition",
                "paramnames": []
            },
            "vars": {
                "": null
            }
        },
        "kind": "function",
        "access": "public",
        "name": "toString",
        "longname": "Channel#toString",
        "memberof": "Channel",
        "scope": "instance",
        "params": []
    },
    {
        "comment": "/**\n   * @method\n   * @public\n   */",
        "meta": {
            "range": [
                8251,
                8580
            ],
            "filename": "Channel.js",
            "lineno": 371,
            "columnno": 2,
            "path": "/home/runner/work/gluon/gluon/src/structures",
            "code": {
                "id": "astnode100000758",
                "name": "Channel#toJSON",
                "type": "MethodDefinition",
                "paramnames": []
            },
            "vars": {
                "": null
            }
        },
        "kind": "function",
        "access": "public",
        "name": "toJSON",
        "longname": "Channel#toJSON",
        "memberof": "Channel",
        "scope": "instance",
        "params": []
    },
    {
        "comment": "",
        "meta": {
            "range": [
                8281,
                8292
            ],
            "filename": "Channel.js",
            "lineno": 373,
            "columnno": 6,
            "path": "/home/runner/work/gluon/gluon/src/structures",
            "code": {
                "id": "astnode100000764",
                "name": "id",
                "type": "MemberExpression",
                "value": "this.id"
            }
        },
        "undocumented": true,
        "name": "id",
        "longname": "id",
        "kind": "member",
        "scope": "global"
    },
    {
        "comment": "",
        "meta": {
            "range": [
                8300,
                8315
            ],
            "filename": "Channel.js",
            "lineno": 374,
            "columnno": 6,
            "path": "/home/runner/work/gluon/gluon/src/structures",
            "code": {
                "id": "astnode100000768",
                "name": "type",
                "type": "MemberExpression",
                "value": "this.type"
            }
        },
        "undocumented": true,
        "name": "type",
        "longname": "type",
        "kind": "member",
        "scope": "global"
    },
    {
        "comment": "",
        "meta": {
            "range": [
                8323,
                8338
            ],
            "filename": "Channel.js",
            "lineno": 375,
            "columnno": 6,
            "path": "/home/runner/work/gluon/gluon/src/structures",
            "code": {
                "id": "astnode100000772",
                "name": "name",
                "type": "MemberExpression",
                "value": "this.name"
            }
        },
        "undocumented": true,
        "name": "name",
        "longname": "name",
        "kind": "member",
        "scope": "global"
    },
    {
        "comment": "",
        "meta": {
            "range": [
                8346,
                8363
            ],
            "filename": "Channel.js",
            "lineno": 376,
            "columnno": 6,
            "path": "/home/runner/work/gluon/gluon/src/structures",
            "code": {
                "id": "astnode100000776",
                "name": "topic",
                "type": "MemberExpression",
                "value": "this.topic"
            }
        },
        "undocumented": true,
        "name": "topic",
        "longname": "topic",
        "kind": "member",
        "scope": "global"
    },
    {
        "comment": "",
        "meta": {
            "range": [
                8371,
                8413
            ],
            "filename": "Channel.js",
            "lineno": 377,
            "columnno": 6,
            "path": "/home/runner/work/gluon/gluon/src/structures",
            "code": {
                "id": "astnode100000780",
                "name": "rate_limit_per_user",
                "type": "MemberExpression",
                "value": "this.rateLimitPerUser"
            }
        },
        "undocumented": true,
        "name": "rate_limit_per_user",
        "longname": "rate_limit_per_user",
        "kind": "member",
        "scope": "global"
    },
    {
        "comment": "",
        "meta": {
            "range": [
                8421,
                8458
            ],
            "filename": "Channel.js",
            "lineno": 378,
            "columnno": 6,
            "path": "/home/runner/work/gluon/gluon/src/structures",
            "code": {
                "id": "astnode100000784",
                "name": "parent_id",
                "type": "LogicalExpression",
                "value": ""
            }
        },
        "undocumented": true,
        "name": "parent_id",
        "longname": "parent_id",
        "kind": "member",
        "scope": "global"
    },
    {
        "comment": "",
        "meta": {
            "range": [
                8466,
                8496
            ],
            "filename": "Channel.js",
            "lineno": 379,
            "columnno": 6,
            "path": "/home/runner/work/gluon/gluon/src/structures",
            "code": {
                "id": "astnode100000790",
                "name": "_attributes",
                "type": "MemberExpression",
                "value": "this."
            }
        },
        "undocumented": true,
        "name": "_attributes",
        "longname": "_attributes",
        "kind": "member",
        "scope": "global"
    },
    {
        "comment": "",
        "meta": {
            "range": [
                8504,
                8537
            ],
            "filename": "Channel.js",
            "lineno": 380,
            "columnno": 6,
            "path": "/home/runner/work/gluon/gluon/src/structures",
            "code": {
                "id": "astnode100000795",
                "name": "_cacheOptions",
                "type": "MemberExpression",
                "value": "this._cacheOptions"
            }
        },
        "undocumented": true,
        "name": "_cacheOptions",
        "longname": "_cacheOptions",
        "kind": "member",
        "scope": "global"
    },
    {
        "comment": "",
        "meta": {
            "range": [
                8545,
                8568
            ],
            "filename": "Channel.js",
            "lineno": 381,
            "columnno": 6,
            "path": "/home/runner/work/gluon/gluon/src/structures",
            "code": {
                "id": "astnode100000799",
                "name": "messages",
                "type": "MemberExpression",
                "value": "this.messages"
            }
        },
        "undocumented": true,
        "name": "messages",
        "longname": "messages",
        "kind": "member",
        "scope": "global"
    },
    {
        "comment": "",
        "meta": {
            "range": [
                8584,
                8607
            ],
            "filename": "Channel.js",
            "lineno": 386,
            "columnno": 0,
            "path": "/home/runner/work/gluon/gluon/src/structures",
            "code": {
                "id": "astnode100000803",
                "name": "module.exports",
                "type": "Identifier"
            }
        },
        "undocumented": true,
        "name": "exports",
        "longname": "module.exports",
        "kind": "member",
        "memberof": "module",
        "scope": "static"
    },
    {
        "kind": "package",
        "longname": "package:undefined",
        "files": [
            "/home/runner/work/gluon/gluon/src/structures/Channel.js"
        ]
    }
]
